odoo/addons/sale_coupon_order_line_link/README.rst
odoo/addons/sale_coupon_order_line_link/__init__.py
odoo/addons/sale_coupon_order_line_link/__manifest__.py
odoo/addons/sale_coupon_order_line_link/i18n/it.po
odoo/addons/sale_coupon_order_line_link/i18n/sale_coupon_order_line_link.pot
odoo/addons/sale_coupon_order_line_link/models/__init__.py
odoo/addons/sale_coupon_order_line_link/models/sale_order.py
odoo/addons/sale_coupon_order_line_link/readme/CONTRIBUTORS.rst
odoo/addons/sale_coupon_order_line_link/readme/DESCRIPTION.rst
odoo/addons/sale_coupon_order_line_link/readme/ROADMAP.rst
odoo/addons/sale_coupon_order_line_link/reports/__init__.py
odoo/addons/sale_coupon_order_line_link/reports/sale_report.py
odoo/addons/sale_coupon_order_line_link/reports/sale_report_views.xml
odoo/addons/sale_coupon_order_line_link/static/description/icon.png
odoo/addons/sale_coupon_order_line_link/static/description/index.html
odoo/addons/sale_coupon_order_line_link/tests/__init__.py
odoo/addons/sale_coupon_order_line_link/tests/test_coupon_order_line_link.py
odoo/addons/sale_coupon_order_line_link/views/sale_order_views.xml
odoo14_addon_sale_coupon_order_line_link-14.0.1.0.2.dist-info/METADATA
odoo14_addon_sale_coupon_order_line_link-14.0.1.0.2.dist-info/WHEEL
odoo14_addon_sale_coupon_order_line_link-14.0.1.0.2.dist-info/top_level.txt
odoo14_addon_sale_coupon_order_line_link-14.0.1.0.2.dist-info/RECORD
